ergo/__init__.py
ergo/dataset.py
ergo/project.py
ergo/templates.py
ergo/version.py
ergo/views.py
ergo/actions/__init__.py
ergo/actions/clean.py
ergo/actions/compare.py
ergo/actions/create.py
ergo/actions/encode.py
ergo/actions/explore.py
ergo/actions/info.py
ergo/actions/optimize.py
ergo/actions/prepare.py
ergo/actions/relevance.py
ergo/actions/serve.py
ergo/actions/to_fdeep.py
ergo/actions/to_tf.py
ergo/actions/train.py
ergo/actions/view.py
ergo/core/__init__.py
ergo/core/action.py
ergo/core/loader.py
ergo/core/logic.py
ergo/core/multi_model.py
ergo/core/optimizer.py
ergo/core/queue.py
ergo/core/saver.py
ergo/core/template.py
ergo/core/utils.py
ergo_ai-1.13.1.data/scripts/ergo
ergo_ai-1.13.1.dist-info/LICENSE.md
ergo_ai-1.13.1.dist-info/METADATA
ergo_ai-1.13.1.dist-info/WHEEL
ergo_ai-1.13.1.dist-info/top_level.txt
ergo_ai-1.13.1.dist-info/RECORD
