Metadata-Version: 2.1
Name: ergo-ai
Version: 1.13.1
Summary: ergo is a tool that makes deep learning with Keras easier.
Home-page: http://www.github.com/evilsocket/ergo
Author: Simone Margaritelli
Author-email: evilsocket@gmail.com
License: GPL
Platform: UNKNOWN
Classifier: Programming Language :: Python :: 3
Classifier: Development Status :: 5 - Production/Stable
Classifier: License :: OSI Approved :: GNU General Public License (GPL)
Classifier: Environment :: Console
Requires-Dist: tensorflow (>2)
Requires-Dist: pandas
Requires-Dist: sklearn
Requires-Dist: pydot
Requires-Dist: matplotlib
Requires-Dist: flask
Requires-Dist: terminaltables
Requires-Dist: seaborn
Requires-Dist: pyyaml
